CHANGELOG.md
LICENSE.md
MANIFEST.in
README.md
setup.cfg
setup.py
django_updown_ratings.egg-info/PKG-INFO
django_updown_ratings.egg-info/SOURCES.txt
django_updown_ratings.egg-info/dependency_links.txt
django_updown_ratings.egg-info/not-zip-safe
django_updown_ratings.egg-info/top_level.txt
tests/__init__.py
tests/conftest.py
tests/models.py
tests/test_model.py
updown/__init__.py
updown/exceptions.py
updown/fields.py
updown/forms.py
updown/models.py
updown/views.py
updown/migrations/0001_initial.py
updown/migrations/__init__.py