Metadata-Version: 2.1
Name: django-updown-ratings
Version: 1.0.0
Summary: Reusable Django application for youtube like up and down voting.
Home-page: http://github.com/agusmakmun/django-updown-ratings/tree/master
Author: Daniel Banck, Agus Makmun
Author-email: dbanck@weluse.de
License: UNKNOWN
Platform: UNKNOWN
Classifier: Development Status :: 5 - Production/Stable
Classifier: Environment :: Web Environment
Classifier: Framework :: Django
Classifier: Intended Audience :: Developers
Classifier: License :: OSI Approved :: BSD License
Classifier: Operating System :: OS Independent
Classifier: Programming Language :: Python
Classifier: Programming Language :: Python :: 3
Classifier: Topic :: Internet :: WWW/HTTP
